LICENSE
MANIFEST.in
README.md
dnseval.py
dnsping.py
dnstraceroute.py
public-servers.txt
public-v4.txt
pyproject.toml
rootservers.txt
dnsdiag/__init__.py
dnsdiag/dns.py
dnsdiag/shared.py
dnsdiag/whois.py
dnsdiag.egg-info/PKG-INFO
dnsdiag.egg-info/SOURCES.txt
dnsdiag.egg-info/dependency_links.txt
dnsdiag.egg-info/entry_points.txt
dnsdiag.egg-info/requires.txt
dnsdiag.egg-info/top_level.txt
tests/test_dnseval_pytest.py
tests/test_dnsping_pytest.py
tests/test_dnstraceroute_pytest.py
tests/test_packaging.py
tests/test_shared.py