Metadata-Version: 2.4
Name: dnsdiag
Version: 2.9.2
Summary: DNS Measurement, Troubleshooting and Security Auditing Toolset (ping, traceroute)
Author-email: Babak Farrokhi <babak@farrokhi.net>
License-Expression: BSD-2-Clause
Project-URL: Homepage, https://dnsdiag.org/
Project-URL: Repository, https://github.com/farrokhi/dnsdiag
Project-URL: Issues, https://github.com/farrokhi/dnsdiag/issues
Keywords: dns,traceroute,ping,performance
Classifier: Topic :: System :: Networking
Classifier: Environment :: Console
Classifier: Intended Audience :: Developers
Classifier: Programming Language :: Python :: 3.10
Classifier: Programming Language :: Python :: 3.11
Classifier: Programming Language :: Python :: 3.12
Classifier: Programming Language :: Python :: 3.13
Classifier: Programming Language :: Python :: 3.14
Classifier: Topic :: Internet :: Name Service (DNS)
Classifier: Development Status :: 5 - Production/Stable
Classifier: Operating System :: OS Independent
Requires-Python: >=3.10
License-File: LICENSE
Requires-Dist: aioquic>=1.2.0
Requires-Dist: cryptography<47,>=42.0.5
Requires-Dist: cymruwhois>=1.6
Requires-Dist: dnspython>=2.8.0
Requires-Dist: h2>=4.1.0
Requires-Dist: httpx>=0.27.0
Dynamic: license-file
